spatialvista/__init__.py
spatialvista/_logger.py
spatialvista/exporter.py
spatialvista/validation.py
spatialvista/visualize.py
spatialvista/widget.py
spatialvista/_widget/spatialvista_widget.mjs
spatialvista-0.1.1.dist-info/METADATA
spatialvista-0.1.1.dist-info/WHEEL
spatialvista-0.1.1.dist-info/top_level.txt
spatialvista-0.1.1.dist-info/RECORD
