Metadata-Version: 2.4
Name: spatialvista
Version: 0.1.1
Summary: 3D ST Visualization in Jupyter
Project-URL: Homepage, https://github.com/JianYang-Lab/spatial-vista-py
Project-URL: Documentation, https://github.com/JianYang-Lab/spatial-vista-py
Project-URL: Repository, https://github.com/JianYang-Lab/spatial-vista-py
Project-URL: Issues, https://github.com/JianYang-Lab/spatial-vista-py/issues
Requires-Python: >=3.10
Requires-Dist: anywidget>=0.9.21
Requires-Dist: laspy[lazrs]>=2.6.1
Requires-Dist: loguru>=0.7.3
Requires-Dist: numpy>=2.2.6
Requires-Dist: pandas>=2.3.3
Requires-Dist: traitlets>=5.14.3
Provides-Extra: docs
Requires-Dist: mkdocs; extra == "docs"
Requires-Dist: mkdocs-material; extra == "docs"
Requires-Dist: mkdocstrings[python]; extra == "docs"
